README.md
setup.py
benchmarks/__init__.py
benchmarks/power.py
mgc/__init__.py
mgc/_utils.py
mgc.egg-info/PKG-INFO
mgc.egg-info/SOURCES.txt
mgc.egg-info/dependency_links.txt
mgc.egg-info/requires.txt
mgc.egg-info/top_level.txt
mgc/independence/__init__.py
mgc/independence/_utils.py
mgc/independence/base.py
mgc/independence/cca.py
mgc/independence/dcorr.py
mgc/independence/hhg.py
mgc/independence/hsic.py
mgc/independence/kendall.py
mgc/independence/pearson.py
mgc/independence/rv.py
mgc/independence/spearman.py
mgc/independence/tests/__init__.py
mgc/independence/tests/test_cca.py
mgc/independence/tests/test_dcorr.py
mgc/independence/tests/test_hhg.py
mgc/independence/tests/test_hsic.py
mgc/independence/tests/test_kendall.py
mgc/independence/tests/test_pearson.py
mgc/independence/tests/test_rvcorr.py
mgc/independence/tests/test_spearman.py
mgc/ksample/__init__.py
mgc/ksample/_utils.py
mgc/ksample/base.py
mgc/ksample/ksamp.py
mgc/ksample/tests/__init__.py
mgc/ksample/tests/test_ksamp.py
mgc/sims/__init__.py
mgc/sims/indep_sim.py
mgc/sims/ksample_sim.py
mgc/sims/tests/__init__.py
mgc/sims/tests/test_indep_sim.py
mgc/sims/tests/test_ksample_sim.py
mgc/time_series/__init__.py
mgc/time_series/_utils.py
mgc/time_series/base.py
mgc/time_series/dcorrx.py
mgc/time_series/tests/__init__.py
mgc/time_series/tests/test_dcorrx.py