Metadata-Version: 2.1
Name: mgc
Version: 0.0.1
Summary: A comprehensive independence testing package
Home-page: https://github.com/sampan501/mgc
Author: ('Sambit Panda',)
Author-email: spanda3@jhu.edu
License: MIT
Platform: UNKNOWN
Classifier: Development Status :: 3 - Alpha
Classifier: Intended Audience :: Science/Research
Classifier: Topic :: Scientific/Engineering :: Mathematics
Classifier: License :: OSI Approved :: Apache Software License
Classifier: Programming Language :: Python :: 3
Classifier: Programming Language :: Python :: 3.5
Classifier: Programming Language :: Python :: 3.6
Classifier: Programming Language :: Python :: 3.7
